ros2bagcut/__init__.py
ros2bagcut/_version.py
ros2bagcut/main.py
ros2bagcut-1.0.0.dist-info/LICENSE
ros2bagcut-1.0.0.dist-info/METADATA
ros2bagcut-1.0.0.dist-info/WHEEL
ros2bagcut-1.0.0.dist-info/entry_points.txt
ros2bagcut-1.0.0.dist-info/top_level.txt
ros2bagcut-1.0.0.dist-info/RECORD
