Metadata-Version: 2.1
Name: ros2bagcut
Version: 1.0.0
Summary: A tool that simply cuts rosbag files within a specified start and end date and time.
Author-email: Katsuya Hyodo <rmsdh122@yahoo.co.jp>
License: MIT License
Project-URL: Homepage, https://github.com/PINTO0309/ros2bagcut
Classifier: Programming Language :: Python :: 3
Requires-Python: >=3.10
License-File: LICENSE
Requires-Dist: pytz >=2022.1
Requires-Dist: rosbag2-py >=0.15.8
